djangocms_export_page/__init__.py
djangocms_export_page/apps.py
djangocms_export_page/cms_toolbars.py
djangocms_export_page/constants.py
djangocms_export_page/mixins.py
djangocms_export_page/settings.py
djangocms_export_page/urls.py
djangocms_export_page/utils.py
djangocms_export_page/views.py
djangocms_export_page/export/__init__.py
djangocms_export_page/export/common.py
djangocms_export_page/export/docx.py
djangocms_export_page/tests/__init__.py
djangocms_export_page-0.2.4.dist-info/licenses/LICENSE
djangocms_export_page-0.2.4.dist-info/METADATA
djangocms_export_page-0.2.4.dist-info/WHEEL
djangocms_export_page-0.2.4.dist-info/top_level.txt
djangocms_export_page-0.2.4.dist-info/RECORD
