Metadata-Version: 2.4
Name: djangocms-export-page
Version: 0.2.4
Summary: Export a Django CMS page or a model view to a DOCX document
Author-email: Maykin Media <support@maykinmedia.nl>
License: Copyright {% now "Y" %} Maykin Media
Project-URL: Homepage, https://github.com/maykinmedia/djangocms-export-page
Project-URL: Bug Tracker, https://github.com/maykinmedia/djangocms-export-page/issues
Project-URL: Source Code, https://github.com/maykinmedia/djangocms-export-page
Keywords: django cms export docx
Classifier: Development Status :: 4 - Beta
Classifier: Framework :: Django
Classifier: Framework :: Django :: 3.2
Classifier: Framework :: Django :: 4.2
Classifier: Intended Audience :: Developers
Classifier: Operating System :: Unix
Classifier: Operating System :: MacOS
Classifier: Operating System :: Microsoft :: Windows
Classifier: Programming Language :: Python :: 3.11
Classifier: Topic :: Software Development :: Libraries :: Python Modules
Requires-Python: >=3.10
License-File: LICENSE
Requires-Dist: django>=3.2
Requires-Dist: django-cms>=4.1
Requires-Dist: djangocms-alias
Requires-Dist: djangocms-page-meta-maykin
Requires-Dist: python-docx
Provides-Extra: tests
Requires-Dist: pytest; extra == "tests"
Requires-Dist: pytest-django; extra == "tests"
Requires-Dist: pytest-cov; extra == "tests"
Requires-Dist: factory-boy; extra == "tests"
Requires-Dist: django-autoslug; extra == "tests"
Requires-Dist: djangocms-text-ckeditor; extra == "tests"
Requires-Dist: tox; extra == "tests"
Requires-Dist: isort; extra == "tests"
Requires-Dist: black; extra == "tests"
Requires-Dist: flake8; extra == "tests"
Provides-Extra: docs
Requires-Dist: sphinx; extra == "docs"
Requires-Dist: sphinx-rtd-theme; extra == "docs"
Provides-Extra: release
Requires-Dist: bump-my-version; extra == "release"
Dynamic: license-file
